{
  "id": "kerbs_and_crossings",
  "maintainer": "Robin van der Linde",
  "version": "20211215",
  "title": {
    "en": "Kerbs and crossings",
    "nl": "Stoepranden en oversteekplaatsen",
    "de": "Bordsteine und Überwege",
    "fr": "Ressauts et traversées"
  },
  "description": {
    "en": "A map showing kerbs and crossings.",
    "nl": "Een kaart met stoepranden en oversteekplaatsen.",
    "de": "Eine Karte mit Bordsteinen und Überwegen.",
    "fr": "Une carte affichant les ressauts et traversées."
  },
  "icon": "./assets/layers/kerbs/KerbIcon.svg",
  "startZoom": 19,
  "startLat": 53.23776,
  "startLon": 6.53812,
  "layers": [
    {
      "builtin": "crossings",
      "override": {
        "=presets": [],
        "source": {
          "osmTags": "highway=crossing"
        }
      }
    },
    "kerbs"
  ]
}