[{"id":89427211,"type":"Feature","geometry":null,"properties":{"check_user":null,"reasons":[{"id":40,"name":"New mapper"}],"tags":[],"features":[],"user":"Decardo","uid":"11653319","editor":"MapComplete 0.0.0","comment":"Beantwoorden van vragen met #MapComplete voor vragenset #buurtnatuur","comments_count":null,"source":"Not reported","imagery_used":"Not reported","date":"2020-08-14T19:28:06Z","reviewed_features":[],"tag_changes":{},"create":0,"modify":0,"delete":0,"area":null,"is_suspect":true,"harmful":null,"checked":false,"check_date":null,"id":89427211}},{"id":89427167,"type":"Feature","geometry":null,"properties":{"check_user":null,"reasons":[{"id":40,"name":"New mapper"}],"tags":[],"features":[],"user":"Decardo","uid":"11653319","editor":"MapComplete 0.0.0","comment":"Beantwoorden van vragen met #MapComplete voor vragenset #buurtnatuur","comments_count":null,"source":"Not reported","imagery_used":"Not reported","date":"2020-08-14T19:26:49Z","reviewed_features":[],"tag_changes":{},"create":0,"modify":0,"delete":0,"area":null,"is_suspect":true,"harmful":null,"checked":false,"check_date":null,"id":89427167}},{"id":89427074,"type":"Feature","geometry":{"type":"Polygon","coordinates":[[[5.2070696,51.1858295],[5.2091316,51.1858295],[5.2091316,51.1872228],[5.2070696,51.1872228],[5.2070696,51.1858295]]]},"properties":{"check_user":null,"reasons":[{"id":40,"name":"New mapper"}],"tags":[],"features":[],"user":"Decardo","uid":"11653319","editor":"MapComplete 0.0.0","comment":"Beantwoorden van vragen met #MapComplete voor vragenset #buurtnatuur","comments_count":null,"source":"Not reported","imagery_used":"Not reported","date":"2020-08-14T19:24:11Z","reviewed_features":[],"tag_changes":{},"create":0,"modify":1,"delete":0,"area":0.00000287298460000827,"is_suspect":true,"harmful":null,"checked":false,"check_date":null,"id":89427074}},{"id":89417205,"type":"Feature","geometry":{"type":"Polygon","coordinates":[[[3.4815663,51.502385],[3.4815663,51.502385],[3.4815663,51.502385],[3.4815663,51.502385],[3.4815663,51.502385]]]},"properties":{"check_user":null,"reasons":[],"tags":[],"features":[],"user":"Kathelijne","uid":"6761922","editor":"MapComplete 0.0.0","comment":"Beantwoorden van vragen met #MapComplete voor vragenset #artworks","comments_count":null,"source":"Not reported","imagery_used":"Not reported","date":"2020-08-14T14:40:56Z","reviewed_features":[],"tag_changes":{},"create":0,"modify":1,"delete":0,"area":0,"is_suspect":false,"harmful":null,"checked":false,"check_date":null,"id":89417205}},{"id":89417169,"type":"Feature","geometry":{"type":"Polygon","coordinates":[[[3.4815663,51.502385],[3.4815663,51.502385],[3.4815663,51.502385],[3.4815663,51.502385],[3.4815663,51.502385]]]},"properties":{"check_user":null,"reasons":[],"tags":[],"features":[],"user":"Kathelijne","uid":"6761922","editor":"MapComplete 0.0.0","comment":"Beantwoorden van vragen met #MapComplete voor vragenset #artworks","comments_count":null,"source":"Not reported","imagery_used":"Not reported","date":"2020-08-14T14:40:09Z","reviewed_features":[],"tag_changes":{},"create":1,"modify":0,"delete":0,"area":0,"is_suspect":false,"harmful":null,"checked":false,"check_date":null,"id":89417169}}]