[{"id":115686930,"type":"Feature","geometry":{"type":"Polygon","coordinates":[[[3.2076481,51.2496923],[3.2089415,51.2496923],[3.2089415,51.2506589],[3.2076481,51.2506589],[3.2076481,51.2496923]]]},"properties":{"check_user":null,"reasons":[],"tags":[],"features":[],"user":"Pieter Vander Vennet","uid":"3818858","editor":"MapComplete 0.13.0-alpha-10","comment":"Adding data with #MapComplete for theme #waste","comments_count":0,"source":"Not reported","imagery_used":"Not reported","date":"2022-01-02T21:51:25Z","reviewed_features":[],"tag_changes":{},"create":0,"modify":1,"delete":0,"area":0.0000012502004399974,"is_suspect":false,"harmful":null,"checked":false,"check_date":null,"host":"pietervdvn.github.io","path":"mc/waste-theme/","theme":"waste","answer":1,"imagery":"AGIV","language":"nl","id":115686930}},{"id":115685951,"type":"Feature","geometry":{"type":"Polygon","coordinates":[[[6.1320726,50.6674774],[6.1324641,50.6674774],[6.1324641,50.6676637],[6.1320726,50.6676637],[6.1320726,50.6674774]]]},"properties":{"check_user":null,"reasons":[],"tags":[],"features":[],"user":"Pieter Vander Vennet","uid":"3818858","editor":"MapComplete 0.12.13","comment":"Adding data with #MapComplete for theme #grb","comments_count":0,"source":"Not reported","imagery_used":"Not reported","date":"2022-01-02T21:11:03Z","reviewed_features":[],"tag_changes":{},"create":11,"modify":10,"delete":0,"area":7.29364499983562e-8,"is_suspect":false,"harmful":null,"checked":false,"check_date":null,"host":"mapcomplete.osm.be","move":10,"theme":"grb","imagery":"osm","language":"en","conflation":4,"id":115685951}},{"id":115681205,"type":"Feature","geometry":{"type":"Polygon","coordinates":[[[14.2640094,40.9390231],[14.2776374,40.9390231],[14.2776374,40.9468637],[14.2640094,40.9468637],[14.2640094,40.9390231]]]},"properties":{"check_user":null,"reasons":[],"tags":[],"features":[],"user":"Acheloo","uid":"11366923","editor":"MapComplete 0.12.13","comment":"Adding data with #MapComplete for theme #etymology","comments_count":0,"source":"Not reported","imagery_used":"Not reported","date":"2022-01-02T18:30:12Z","reviewed_features":[],"tag_changes":{},"create":0,"modify":5,"delete":0,"area":0.000106851696800012,"is_suspect":false,"harmful":null,"checked":false,"check_date":null,"host":"mapcomplete.osm.be","theme":"etymology","answer":8,"imagery":"osm","language":"en","id":115681205}},{"id":115680001,"type":"Feature","geometry":{"type":"Polygon","coordinates":[[[2.9503493,50.385791],[3.1552182,50.385791],[3.1552182,50.7488441],[2.9503493,50.7488441],[2.9503493,50.385791]]]},"properties":{"check_user":null,"reasons":[],"tags":[],"features":[],"user":"whatismoss","uid":"8427311","editor":"MapComplete 0.12.13","comment":"Adding data with #MapComplete for theme #etymology","comments_count":0,"source":"Not reported","imagery_used":"Not reported","date":"2022-01-02T17:56:01Z","reviewed_features":[],"tag_changes":{},"create":0,"modify":66,"delete":0,"area":0.0743782892385904,"is_suspect":false,"harmful":null,"checked":false,"check_date":null,"host":"mapcomplete.osm.be","theme":"etymology","answer":120,"imagery":"osm","language":"en","id":115680001}},{"id":115676863,"type":"Feature","geometry":{"type":"Polygon","coordinates":[[[6.4611304,51.1024626],[6.4611304,51.1024626],[6.4611304,51.1024626],[6.4611304,51.1024626],[6.4611304,51.1024626]]]},"properties":{"check_user":null,"reasons":[],"tags":[],"features":[],"user":"Pieter Vander Vennet","uid":"3818858","editor":"MapComplete 0.13.0-alpha-10","comment":"Adding data with #MapComplete for theme #food","comments_count":0,"source":"survey","imagery_used":"Not reported","date":"2022-01-02T16:24:37Z","reviewed_features":[],"tag_changes":{},"create":1,"modify":2,"delete":0,"area":0,"is_suspect":false,"harmful":null,"checked":false,"check_date":null,"host":"pietervdvn.github.io","path":"mc/develop/","theme":"food","answer":4,"imagery":"osm","language":"en","change_over_5000m":1,"change_within_25m":4,"id":115676863}},{"id":115674924,"type":"Feature","geometry":{"type":"Polygon","coordinates":[[[4.7485918,51.161045],[4.7492398,51.161045],[4.7492398,51.161444],[4.7485918,51.161444],[4.7485918,51.161045]]]},"properties":{"check_user":null,"reasons":[],"tags":[],"features":[],"user":"Stinus_Clasius","uid":"1086503","editor":"MapComplete 0.12.13","comment":"Adding data with #MapComplete for theme #grb","comments_count":0,"source":"Not reported","imagery_used":"Not reported","date":"2022-01-02T15:35:59Z","reviewed_features":[],"tag_changes":{},"create":16,"modify":18,"delete":0,"area":2.58552000001025e-7,"is_suspect":false,"harmful":null,"checked":false,"check_date":null,"host":"mapcomplete.osm.be","move":14,"theme":"grb","imagery":"AGIV","language":"nl","conflation":8,"id":115674924}},{"id":115673330,"type":"Feature","geometry":{"type":"Polygon","coordinates":[[[6.5404004,53.0068628],[6.5404004,53.0068628],[6.5404004,53.0068628],[6.5404004,53.0068628],[6.5404004,53.0068628]]]},"properties":{"check_user":null,"reasons":[],"tags":[],"features":[],"user":"Robin van der Linde","uid":"5093765","editor":"MapComplete 0.13.0-alpha-10","comment":"Adding data with #MapComplete for theme #waste","comments_count":0,"source":"survey","imagery_used":"Not reported","date":"2022-01-02T14:58:52Z","reviewed_features":[],"tag_changes":{},"create":1,"modify":1,"delete":0,"area":0,"is_suspect":false,"harmful":null,"checked":false,"check_date":null,"host":"pietervdvn.github.io","path":"mc/waste-theme/","theme":"waste","answer":3,"imagery":"osm","language":"nl","change_over_5000m":1,"change_within_50m":3,"id":115673330}},{"id":115672066,"type":"Feature","geometry":{"type":"Polygon","coordinates":[[[14.6332871,51.7322831],[14.6373429,51.7322831],[14.6373429,51.734292],[14.6332871,51.734292],[14.6332871,51.7322831]]]},"properties":{"check_user":null,"reasons":[],"tags":[],"features":[],"user":"sebkur","uid":"22917","editor":"MapComplete 0.7.2l","comment":"Adding data with #MapComplete for theme #waldbrand","comments_count":0,"source":"survey","imagery_used":"Not reported","date":"2022-01-02T14:30:51Z","reviewed_features":[],"tag_changes":{},"create":3,"modify":4,"delete":0,"area":0.00000814769662002773,"is_suspect":false,"harmful":null,"checked":false,"check_date":null,"host":"waldbrand-app.de","theme":"waldbrand","imagery":"osm","language":"de","theme-creator":"Sebastian Kürten","id":115672066}},{"id":115665991,"type":"Feature","geometry":{"type":"Polygon","coordinates":[[[6.093939,50.7782419],[6.093939,50.7782419],[6.093939,50.7782419],[6.093939,50.7782419],[6.093939,50.7782419]]]},"properties":{"check_user":null,"reasons":[],"tags":[],"features":[],"user":"Pieter Vander Vennet","uid":"3818858","editor":"MapComplete 0.13.0-alpha-10","comment":"Adding data with #MapComplete for theme #ghostbikes","comments_count":0,"source":"survey","imagery_used":"Not reported","date":"2022-01-02T11:53:43Z","reviewed_features":[],"tag_changes":{},"create":0,"modify":2,"delete":0,"area":0,"is_suspect":false,"harmful":null,"checked":false,"check_date":null,"host":"pietervdvn.github.io","path":"mc/develop/","theme":"ghostbikes","imagery":"CartoDB.Positron","language":"en","add-image":2,"change_within_25m":2,"id":115665991}},{"id":115658538,"type":"Feature","geometry":{"type":"Polygon","coordinates":[[[-111.943619,33.4591777],[-111.943619,33.4591777],[-111.943619,33.4591777],[-111.943619,33.4591777],[-111.943619,33.4591777]]]},"properties":{"check_user":null,"reasons":[{"id":43,"name":"Invalid key value combination"}],"tags":[],"features":[{"url":"node-9371314839","osm_id":9371314839,"reasons":[43],"version":2,"primary_tags":{"amenity":"binoculars"}}],"user":"mycota","uid":"7541348","editor":"MapComplete 0.12.13","comment":"Adding data with #MapComplete for theme #binoculars","comments_count":0,"source":"survey","imagery_used":"Not reported","date":"2022-01-02T06:03:16Z","reviewed_features":[],"tag_changes":{},"create":0,"modify":1,"delete":0,"area":0,"is_suspect":false,"harmful":null,"checked":false,"check_date":null,"host":"mapcomplete.osm.be","theme":"binoculars","answer":2,"imagery":"osm","language":"en","change_within_5000m":2,"id":115658538}},{"id":115656452,"type":"Feature","geometry":{"type":"Polygon","coordinates":[[[-111.9454006,33.4624688],[-111.9454,33.4624688],[-111.9454,33.4624688],[-111.9454006,33.4624688],[-111.9454006,33.4624688]]]},"properties":{"check_user":null,"reasons":[],"tags":[],"features":[],"user":"mycota","uid":"7541348","editor":"MapComplete 0.12.13","comment":"Adding data with #MapComplete for theme #cyclofix","comments_count":0,"source":"survey","imagery_used":"Not reported","date":"2022-01-02T02:12:27Z","reviewed_features":[],"tag_changes":{},"create":0,"modify":1,"delete":0,"area":0,"is_suspect":false,"harmful":null,"checked":false,"check_date":null,"host":"mapcomplete.osm.be","theme":"cyclofix","answer":2,"imagery":"CartoDB.Voyager","language":"en","change_within_5000m":2,"id":115656452}}]