[{"id":90661800,"type":"Feature","geometry":{"type":"Polygon","coordinates":[[[3.2224005,51.2067593],[3.2282317,51.2067593],[3.2282317,51.2086872],[3.2224005,51.2086872],[3.2224005,51.2067593]]]},"properties":{"check_user":null,"reasons":[],"tags":[],"features":[],"user":"Pieter Vander Vennet","uid":"3818858","editor":"MapComplete 0.0.7k","comment":"Adding data with #MapComplete for theme #cyclofix","comments_count":null,"source":"Not reported","imagery_used":"Not reported","date":"2020-09-09T18:45:49Z","reviewed_features":[],"tag_changes":{},"create":2,"modify":8,"delete":0,"area":0.0000112419704799898,"is_suspect":false,"harmful":null,"checked":false,"check_date":null,"theme":"cyclofix","id":90661800}},{"id":90652529,"type":"Feature","geometry":{"type":"Polygon","coordinates":[[[8.2973613,47.0467053],[8.3086603,47.0467053],[8.3086603,47.0495842],[8.2973613,47.0495842],[8.2973613,47.0467053]]]},"properties":{"check_user":null,"reasons":[],"tags":[],"features":[],"user":"Marcus Fihlon","uid":"1935779","editor":"MapComplete 0.0.7h","comment":"Adding data with #MapComplete for theme #cyclofix","comments_count":null,"source":"Not reported","imagery_used":"Not reported","date":"2020-09-09T14:35:31Z","reviewed_features":[],"tag_changes":{},"create":0,"modify":21,"delete":0,"area":0.0000325286910999856,"is_suspect":false,"harmful":null,"checked":false,"check_date":null,"theme":"cyclofix","id":90652529}}]