{"BAC Credomatic":19,"Banco Azteca":8,"Banco de Occidente":36,"Banpais":14,"Banrural":10,"Baskin-Robbins":5,"Burger King":27,"Church's Chicken":9,"Cinemark":4,"Cinnabon":3,"Circle K":10,"Citibank":4,"Claro":9,"Comex":3,"Cruz Roja Hondureña":8,"DHL":3,"Davivienda":17,"Denny's":4,"Despensa Familiar":13,"Domino's":5,"Dunkin'":7,"Elektra":4,"Farmacity":3,"FedEx":5,"Ficohsa":13,"Ford":3,"KFC":11,"Kia":3,"La Curacao":8,"Little Caesars":18,"McDonald's":13,"Papa John's":4,"Payless ShoeSource":3,"Pizza Hut":28,"Pollo Campero":6,"Popeyes":10,"Puma":85,"Punto Farma":9,"Quiznos":3,"RadioShack":3,"Sherwin-Williams":5,"Star Mart":3,"Subway":15,"Texaco":60,"Toyota":3,"Uno":62,"Walmart":5,"Wendy's":20,"Western Union":9,"undefined":731}