{"A CELER":20,"A LORD":17,"ACES Porto Ocidental":10,"ALDI":8,"Acciona Energia Portugal":17,"Adif":9,"Agrupamento de Escolas Coimbra Centro":21,"Agrupamento de Escolas Coimbra Oeste":16,"Agrupamento de Escolas Viseu Norte":25,"Agrupamento de Escolas de Anadia":21,"Agrupamento de Escolas de Arouca":11,"Agrupamento de Escolas de Castro Daire":13,"Agrupamento de Escolas de Celorico de Basto":18,"Agrupamento de Escolas de Coruche":14,"Agrupamento de Escolas de Montemor-o-Novo":17,"Agrupamento de Escolas de Oliveira do Bairro":12,"Agrupamento de Escolas de Oliveira do Hospital":19,"Agrupamento de Escolas de Ourém":16,"Agrupamento de Escolas de Pombal":17,"Agrupamento de Escolas de Porto de Mós":22,"Agrupamento de Escolas de Tondela Cândido de Figueiredo":21,"Agrupamento de Escolas de Vagos":17,"Agrupamento de Escolas de Vila Verde":17,"Agrupamento de Escolas do Cadaval":13,"Agrupamento de Escolas do Concelho de Caminha":15,"Akuo Renováveis Portugal":15,"Aldi":12,"Algar":47,"Altice Portugal":79,"Amarsul":23,"Amazon":4,"Aquila Capital":20,"Atlante":485,"Auchan":14,"BP":110,"Bluecharge":13,"Burger King":12,"CTT":775,"Cepsa":78,"Charging Together":120,"Comboios de Portugal":112,"Consellería de Educación e Ordenación Universitaria":3,"Correos":3,"Câmara Municipal de Lisboa":605,"DHL":3,"DPD":8,"DRA/DRAM":28,"DRRF":34,"Decathlon":6,"DomusVi":7,"E-Plug":28,"E-REDES":29017,"E.Leclerc":3,"EDP":1770,"EDP Renováveis":63,"EMEL":2754,"EPAL":120,"ERSUC":21,"EV Power":28,"EcoInside":36,"Ecobeirão":24,"Eletricidade dos Açores":143,"Emacom":19,"Enagas":3,"Energias de Portugal":142,"Energiekontor":6,"Escola Básica Integrada da Praia da Vitória":13,"Evio":13,"Factor Energia":39,"Finerge":21,"GLS":3,"Galp Geste":168,"Galp Power":768,"Generation Journey":21,"Generg":26,"Gesamb":266,"GreenCharge":17,"Guarda Nacional Republicana":545,"Helexia II":100,"Hexagonal Ocean":22,"High Green Power":16,"IKEA":14,"Iberdrola":185,"Infraestruturas de Portugal":656,"Instituto da Conservação da Natureza e das Florestas":94,"Instituto das Florestas e Conservação da Natureza, IP-RAM":13,"Intermarché":59,"JCDecaux":6,"Junta de Extremadura":4,"Junta de Freguesia de Faiões":20,"KLC Serviços":304,"LIPOR":25,"Leroy Merlin":4,"Lidl":42,"Loulé Concelho Global":24,"MRW":7,"Maksu Services":67,"McDonald's":12,"Mercadona":10,"Ministério da Justiça":19,"Ministério da Saúde":70,"Mobi.E":9,"MobiSmart":49,"Mobiletric":103,"Moon":28,"Mota Engil II":48,"Neoen":4,"Nissan":12,"Parque Eólico de Gevancas, S.A":12,"Polícia de Segurança Pública":247,"Porsche":33,"Prio.E":125,"REN":3528,"REP":19,"Red Eléctrica de España":37,"Renault":15,"Repsol":271,"Resiestrela":19,"Resinorte":37,"Resíduos do Nordeste":19,"SEGMA":41,"SIMAR":78,"SMAT":4,"Santa Casa da Misericórdia":37,"Secretaria Regional do Ambiente e Recursos Naturais":22,"Servizo Galego de Saúde":3,"Serviço Nacional de Saúde":434,"Serviços Intermunicipalizados de Águas e Resíduos":338,"Simarsul":39,"Sonae":229,"Spar":4,"Suma":10,"Total":3,"TrustWind":19,"Trustenergy":18,"Ucharge":18,"Ultriplo":17,"Valnor":24,"Valorlis":25,"Valorsul":20,"Ventient Energy":46,"Vodafone":19,"Xunta de Galicia":29,"undefined":123040,"Águas Públicas do Alentejo":54,"Águas do Algarve":298,"Águas do Tejo Atlântico":193}